<?xml version="1.0" encoding="UTF-8" standalone="no"?>
<!-- 

  ancoralex-2.0.3
       
			Copyright (C) 2007,2008,2009,2010,2011 CLiC - UB
			Centre de Llenguatge i Computació - Universitat de Barcelona
 
  This file is part of ancoralex-2.0.3.
 
  ancoralex-2.0.3 is free software and data: you can redistribute it and/or modify
  it under the terms of the GNU General Public License as published
  by the Free Software Foundation, either version 3 of the License,
  or (at your option) any later version.

  ancoralex-2.0.3 is distributed in the hope that it will be useful,
  but WITHOUT ANY WARRANTY; without even the implied warranty of
  MERCHANTABILITY or FITNESS FOR A PARTICULAR PURPOSE.  See the
  GNU General Public License for more details.
 
  You should have received a copy of the GNU General Public License
  along with ancoralex-2.0.3.  If not, see &lt;http://www.gnu.org/licenses/&gt;.
 
  Check a text in catalan explaining the terms of the license at http://www.softcatala.cat/wiki/GPL3.
  In spanish at http://www.viti.es/gnu/licenses/gpl.html
  
  The following paper must be cited when using verb lexicon: 

 * Aparicio, Juan, Mariona Taulé, M.Antònia Martí (2008) 'AnCora-Verb: A Lexical Resource for 
   the Semantic Annotation of Corpora'. Proceedings of 6th International Conference on Language 
   Resources and Evaluation. Marrakesh (Morocco).

  The following paper must be cited when using noun lexicon: 

 * Peris, Aina, Mariona Taulé (2011). AnCora-Nom: A Spanish lexicon of deverbal nominalizations. 
   Procesamiento del Lenguaje Natural, nº46, pp. 11-18.
 
 

 

-->

<lexentry lemma="pago" lng="es" origin="deverbal" type="noun">
  <sense cousin="no" denotation="result" id="1" lexicalized="no" originlemma="pagar" originlink="verb.pagar.1" wordnetsynset="16:00725730">
    <frame appearsinplural="yes" type="default">
      <argument argument="arg0" thematicrole="agt">
        <constituent frequency="2" type="sp"/>
      </argument>
      <argument argument="arg1" foundincorporated="yes" thematicrole="pat">
        <constituent frequency="5" preposition="de" type="sp"/>
      </argument>
      <argument argument="argM" thematicrole="ext">
        <constituent frequency="1" preposition="de" type="sp"/>
      </argument>
      <specifiers>
        <constituent frequency="1" postype="indefinite" type="determiner"/>
        <constituent frequency="2" postype="demonstrative" type="determiner"/>
        <constituent frequency="5" postype="article" type="determiner"/>
        <constituent frequency="17" type="void"/>
      </specifiers>
      <reference_modifiers>
        <constituent frequency="2" type="S"/>
      </reference_modifiers>
      <examples>
        <example file="3LB-CAST/104_C-5.tbf.xml" nodepath="14.3.3.0.1.0" sentencenodepath="14">El acuerdo también supone que los accionistas recibirán <argset><specifier>un</specifier><head>pago </head><argument argument="arg1" function="cn" thematicrole="pat" type="sp">de capital</argument><argument argument="argM" function="cn" thematicrole="ext" type="sp">de 90 francos suizos ( 53 dólares )</argument></argset>y un dividendo especial de 135 francos suizos ( unos 80 dólares ) por cada acción de Algroup . </example>
        <example file="3LB-CAST/a1-2.tbf.xml" nodepath="7.0.0.1.3.1.1.2.1.1.0" sentencenodepath="7">Algo que poco tiene_que_ver con la literatura trascendente de <argset><specifier>estos</specifier><head>pagos </head></argset>. </example>
        <example file="3LB-CAST/a1-4.tbf.xml" nodepath="15.2.3.1.2.1.1.0.4.2.1.1.2.1.1.0" sentencenodepath="15">Ø Trabajamos y Germán_de_Granda , desde su aparente exabrupto , es un buen modelo de lo que Ø llamamos cumplimiento del deber , con una fórmula muy olvidada por <argset><specifier>estos</specifier><head>pagos </head></argset>. </example>
        <example file="CESS-CAST-A/14709_20000419.tbf.xml" nodepath="6.0.3.2.1.0" sentencenodepath="6">La relación de la corona con el dólar tiene importancia en la compra de petróleo , ya_que <argset><specifier>los</specifier><head>pagos </head></argset>se hacen en dólares , aunque el encarecimiento de la moneda estadounidense se ve compensado por el bajo precio del crudo , afirma Niedermayer . </example>
        <example file="CESS-CAST-A/18483_20000126.tbf.xml" nodepath="13.3.1.1.1.0.0" sentencenodepath="13">Los dos países han negociado en meses previos las modalidades de <argset><head>pago </head></argset>en reuniones de expertos . </example>
        <example file="CESS-CAST-A/18549_20000922.tbf.xml" nodepath="8.3.1.1.1.2.0.1.1.1.0.0" sentencenodepath="8">Los préstamos se otorgan a_partir_de un análisis que mide la capacidad de <argset><head>pago </head></argset>y el carácter del solicitante . </example>
        <example file="CESS-CAST-A/18549_20000922.tbf.xml" nodepath="10.0.1.3.1.2.0.0.1.1.0.0" sentencenodepath="10">" Con esos elementos se califica el 70_por_ciento del cliente : voluntad de <argset><head>pago </head></argset>y seriedad de la persona en su entorno . El resto es medir su capacidad de pago en_función_de su negocio " , añadió Ribadeneira . </example>
        <example file="CESS-CAST-A/18549_20000922.tbf.xml" nodepath="10.0.3.2.1.1.1.1.0.0" sentencenodepath="10">" Con esos elementos se califica el 70_por_ciento del cliente : voluntad de pago y seriedad de la persona en su entorno . El resto es medir su capacidad de <argset><head>pago </head></argset>en_función_de su negocio " , añadió Ribadeneira . </example>
        <example file="CESS-CAST-A/19061_20000426.tbf.xml" nodepath="8.2.3.3.2.1.1.2.0.0" sentencenodepath="8">El juez recuerda que " según la ley " , las autoescuelas " deben proporcionar a los futuros conductores un mínimo de horas de formación teórica , pero ni se les exige simultáneamente ninguna prueba de capacitación práctica en el manejo del cuadriciclo o ciclomotor ni parece arriesgado afirmar que , a_cambio_del <argset><head>pago </head><argument argument="arg1" function="cn" thematicrole="pat" type="sp">de la correspondiente matrícula</argument></argset>, el control real sobre el resultado de suficiencia del examen teórico sea ilusorio " . </example>
        <example file="CESS-CAST-AA/3976_20000108.tbf.xml" nodepath="10.4.1.1.0.1.1.1.1.0.0" sentencenodepath="10">Y Ø es que la estrategia económica de Mahuad depende en_gran_medida de que el Fondo_Monetario_Internacional ( FMI ) apruebe una carta de intenciones y un crédito de contingencia ( " standby " ) por 250 millones de dólares destinada a apuntalar la balanza de <argset><head>pagos </head></argset>y permitir el inicio de una reactivación económica . </example>
        <example file="CESS-CAST-AA/5498_20000307.tbf.xml" nodepath="3.0.1.2.3.1.1.1.1.0.0" sentencenodepath="3">La producción del cobre , paralizada durante año y medio por la suspensión de <argset><head>pagos </head></argset>de la empresa , se reabrirá en el plazo de un mes o mes y medio aval de 1.000 millones concedido por la Junta_de_Andalucía , que se hizo efectivo ayer tras cerrar un acuerdo con el Banco_de_Andalucía . </example>
        <example file="CESS-CAST-AA/5498_20000307.tbf.xml" nodepath="6.4.1.3.1.1.1.1.0.0" sentencenodepath="6">El crédito ICO es imprescindible , según los mineros , para que la empresa , de la cual los trabajadores son también accionistas , salga de la suspensión de <argset><head>pagos </head></argset>en la que Ø se encuentra . </example>
        <example file="CESS-CAST-AA/6594_20000308.tbf.xml" nodepath="1.4.1.1.2.1.1.2.1.1.3.5.0.0" sentencenodepath="1">En un comunicado , Martínez_Noval se refirió a las informaciones publicadas en los últimos días sobre las relaciones del empresario Javier_de_la_Rosa con un bufete de abogados de Barcelona , en el que , supuestamente , se canalizaban <argset><head>pagos </head></argset>a los ex directivos de la Agencia_Tributaria . </example>
        <example file="CESS-CAST-AA/8633_20000114.tbf.xml" nodepath="5.3.1.2.4.1.1.1.1.0" sentencenodepath="5">Por_su_parte , el Senado ha creado una comisión de investigación que por_ahora ha concedido a los aeropuertos el aplazamiento de <argset><specifier>los</specifier><head>pagos </head><argument argument="arg1" function="cn" thematicrole="pat" type="sp">de tasas e impuestos</argument></argset>. </example>
        <example file="CESS-CAST-P/101_20010401.tbf.xml" nodepath="6.2.1.0.4.2.1.0.0" sentencenodepath="6">La información que reciben los solicitantes es la que obra en poder de la Agencia a 30_de_abril_del_2001 sobre rendimientos de trabajo personal ; de capital mobiliario ; de arrendamientos de inmuebles sometidos a retención o ingreso a cuenta ; de actividades económicas sometidas a retención o ingreso a_cuenta_de indemnizaciones y subvenciones agrícolas ; sobre <argset><head>pagos </head><reference_modifiers>fraccionados</reference_modifiers><argument argument="arg0" function="cn" thematicrole="agt" type="sp">de empresarios , profesionales y agricultores ; de venta de activos financieros</argument></argset>; sobre aportaciones a planes y fondos de pensiones ; y sobre transmisiones y retenciones de fondos de inversión . </example>
        <example file="CESS-CAST-P/102_19990202.tbf.xml" nodepath="21.2.1.0.1.0.3.4.3.1.0.1.1.0.0" sentencenodepath="21">Otra opinión influyente es la del director del Instituto_de_Harvard_para_el_Desarrollo_Internacional , Jeffrey_Sachs , quien pronosticó ayer en Davos que Brasil podría incluso entrar en suspensión del <argset><head>pagos </head></argset>. </example>
        <example file="CESS-CAST-P/105_20000401.tbf.xml" nodepath="0.2.3.1.1.1.1.1.1.0.0" sentencenodepath="0">Una primera lectura del frenazo a la subida de los peajes hace presuponer que el beneficiado es el usuario de la vía de <argset><head>pago </head></argset>. </example>
        <example file="CESS-CAST-P/109_20010301.tbf.xml" nodepath="9.1.0.1.1.1.0.0" sentencenodepath="9">PLAZAS_EN_EL_CENTRO Las 1.500 plazas de <argset><head>pago </head><argument argument="arg1" function="cn" thematicrole="pat" type="sp">de superficie</argument></argset>( zona azul ) de la ciudad , principalmente en el centro urbano , y las 1.893 de los párkings actuales 654 sólo en el Hospital_Parc_Taulí y 511 repartidas en tres pequeños estacionamientos en La_Concòrdia , Sant_Oleguer y la plaza de Mossèn_Geis - - son insuficientes para la demanda . </example>
        <example file="CESS-CAST-P/17_20001201.tbf.xml" nodepath="8.4.5.1.1.1.0.1.3.1.1.1.1.0.1" sentencenodepath="8">La Subdirección_General_del_Ministerio_de_Trabajo se ha manifestado en sentido contrario a dicha interpretación , si_bien Ø no ha hecho cambiar el criterio de aquella , que mantiene la obligación de exteriorizar <argset><reference_modifiers>dichos</reference_modifiers><head>pagos </head></argset>mediante la suscripción de un contrato de seguro o un plan de pensiones . </example>
        <example file="CESS-CAST-P/26_19990701_d.tbf.xml" nodepath="1.0.3.2.1.1.0.0" sentencenodepath="1">Ø Irán a los aparcamientos , al ser de <argset><head>pago </head></argset>; que se escuchen ruidos ; y algún caco como símbolo del posible aumento de la inseguridad ciudadana . </example>
        <example file="CESS-CAST-P/51_20000402.tbf.xml" nodepath="0.4.1.1.2.4.1.1.1.0" sentencenodepath="0">Los máximos dirigentes de UDC se despacharon a_gusto contra los militantes del sector crítico , a los que Ø acusan de haber filtrado <argset><specifier>los</specifier><head argument="arg1" thematicrole="pat">pagos </head><argument argument="arg0" function="cn" thematicrole="agt" type="sp">de Fidel_Pallerols</argument></argset>. </example>
        <example file="CESS-CAST-P/64_19990201.tbf.xml" nodepath="3.0.4.1.2.1.1.1.1.3.2.1.1.1.1.0" sentencenodepath="3">La devaluación progresiva del real frente_al dólar - - en enero la divisa brasileña cayó más del 70% , la sangría incontrolada de capitales y el pánico popular ante los rumores de que el Gobierno confiscaría las cuentas de ahorro y Ø declararía la moratoria en <argset><specifier>los</specifier><head>pagos </head><argument argument="arg1" function="cn" thematicrole="pat" type="sp">de sus deudas</argument></argset>, ha encendido todas las luces de alarma . </example>
        <example file="CESS-CAST-P/69_20010201_f.tbf.xml" nodepath="4.3.0.6.0" sentencenodepath="4">La compañía ofrecerá , a_partir_de Junio , <argset>depósitos en yenes , fondos de inversión , préstamos y <head argument="arg1" thematicrole="pat">pagos </head>
          </argset>. </example>
        <example file="CESS-CAST-P/75_19990901.tbf.xml" nodepath="18.3.1.2.1.0.0" sentencenodepath="18">En este sentido , Ø subrayó los largos plazos de <argset><head>pago </head></argset>que sufren los proveedores de algunas grandes superficies , pese_a la existencia de la ley de comercio que prohíbe esas prácticas . </example>
        <example file="CESS-CAST-P/81_20001001.tbf.xml" nodepath="5.3.1.2.2.5.1.0.2.1.1.1.1.0" sentencenodepath="5">Las asociaciones de mujeres reivindican la creación de un fondo por_parte_del Estado para que , en caso de impago , la Administración les asegure el cobro y Ø se lo exija luego al EX cónyuge obligado a hacer <argset><specifier>el</specifier><head>pago </head></argset>. </example>
      </examples>
    </frame>
  </sense>
  <sense cousin="no" denotation="event" id="2" lexicalized="no" originlemma="pagar" originlink="verb.pagar.1" wordnetsynset="16:00725730">
    <frame appearsinplural="no" type="default">
      <argument argument="arg1" thematicrole="pat">
        <constituent frequency="14" preposition="de" type="sp"/>
      </argument>
      <argument argument="arg2" thematicrole="ben">
        <constituent frequency="2" preposition="a" type="sp"/>
      </argument>
      <specifiers>
        <constituent frequency="10" postype="article" type="determiner"/>
        <constituent frequency="4" type="void"/>
      </specifiers>
      <reference_modifiers>
        <constituent frequency="1" type="S"/>
      </reference_modifiers>
      <examples>
        <example file="3LB-CAST/2000060111_5-3.tbf.xml" nodepath="2.0.0.1.1.1.1.1.0" sentencenodepath="2">La posibilidad de aliviar los costes y de contrarrestar las pérdidas causadas por los bloqueos mediante <argset><specifier>el</specifier><head>pago </head><reference_modifiers>diferido</reference_modifiers><argument argument="arg1" function="cn" thematicrole="pat" type="sp">de aranceles</argument></argset>también es estudiada por el Gobierno , añadió el titular de Agricultura . </example>
        <example file="CESS-CAST-A/11811_20000516.tbf.xml" nodepath="12.4.1.5.1.2.1.0" sentencenodepath="12">El PLD ha sido acusado en las últimas semanas por la oposición de " comprar cédulas " a vecinos de barrios pobres de la capital y otras ciudades a_cambio_de bolsas con alimentos y <argset><specifier>el</specifier><head>pago </head><argument argument="arg1" function="cn" thematicrole="pat" type="sp">de hasta 300 pesos ( unos 18 dólares )</argument></argset>. </example>
        <example file="CESS-CAST-A/12547_20000119.tbf.xml" nodepath="1.0.3.5.1.3.2.1.0" sentencenodepath="1">El coordinador andaluz de IU y candidato a la presidencia de la Junta , Antonio_Romero , aseguró en Málaga que Ø remitirá sendos escritos a Cardenal y al fiscal jefe de la Audiencia_Provincial_de_Sevilla , Alfredo_Flores , para que Ø investiguen si procede <argset><specifier>el</specifier><head>pago </head><argument argument="arg1" function="cn" thematicrole="pat" type="sp">de las ayudas</argument></argset>, y Ø recordó que Ø ya se dirigió a ellos para pedir que se aclarara el retraso en el dictamen pericial por la rotura de la balsa que propició el desastre ecológico . </example>
        <example file="CESS-CAST-AA/21342_20000526.tbf.xml" nodepath="5.4.1.2.1.1.0" sentencenodepath="5">En el sistema de indemnizaciones se podrá fijar , si Ø fuera necesario , para la totalidad o para algunos de los elementos de la indemnización , un límite máximo y mínimo en <argset><specifier>el</specifier><head>pago </head><argument argument="arg1" function="cn" thematicrole="pat" type="sp">de la misma</argument></argset>. </example>
        <example file="CESS-CAST-AA/24699_20000229.tbf.xml" nodepath="2.3.0.1.2.1.1.3.1.0.0" sentencenodepath="2">Ante unas 500 personas , la esposa de José_María_Aznar ha destacado el conocido Decreto_Coste_Cero , iniciativa que ha eximido a las empresas del <argset><head>pago </head><argument argument="arg1" function="cn" thematicrole="pat" type="sp">de cotizaciones empresariales</argument><argument argument="arg2" function="cn" thematicrole="ben" type="sp">a la Seguridad_Social</argument></argset>cuando Ø contraten empleados en sustitución de los que estén de baja por maternidad , o la ley que promueve la conciliación de la vida familiar y laboral de las personas trabajadoras . </example>
        <example file="CESS-CAST-AA/3502_20001106.tbf.xml" nodepath="11.2.1.2.3.4.1.1.1.1.1.1.0" sentencenodepath="11">El Grupo_Socialista ha presentado una enmienda parcial en la que Ø pide que se incremente en 10.000 millones de pesetas la partida destinada a subsidiar <argset><specifier>el</specifier><head>pago </head><argument argument="arg1" function="cn" thematicrole="pat" type="sp">de las hipotecas</argument></argset>, ya_que , según Segura , " la que consignan los presupuestos es muy corta " . </example>
        <example file="CESS-CAST-AA/5166_20001108.tbf.xml" nodepath="9.2.2.0.1.1.0.0" sentencenodepath="9">Ø Agregó que seguirán exentos del <argset><head>pago </head><argument argument="arg1" function="cn" thematicrole="pat" type="sp">del ITBIS</argument></argset>los productos de origen agropecuario y otros alimentos básicos , incluidos la leche y sus derivados , y el arroz , la carne de pollo y las habichuelas , base de la dieta popular dominicana . </example>
        <example file="CESS-CAST-AA/5166_20001108.tbf.xml" nodepath="17.2.2.2.4.1.2.1.0" sentencenodepath="17">Mejía advirtió que se terminó la era de las evasiones fiscales y Ø anunció " la última amnistía fiscal " para quienes han evadido <argset><specifier>el</specifier><head>pago </head><argument argument="arg1" function="cn" thematicrole="pat" type="sp">de los impuestos</argument></argset>. </example>
        <example file="CESS-CAST-AA/8815_20000114.tbf.xml" nodepath="2.2.1.0" sentencenodepath="2">La licencia tipo C implica <argset><specifier>el</specifier><head>pago </head><argument argument="arg1" function="cn" thematicrole="pat" type="sp">de una tasa anual que no excederá del dos_por_mil de sus ingresos brutos de explotación</argument></argset>. </example>
        <example file="CESS-CAST-P/126_20010301.tbf.xml" nodepath="1.3.1.1.1.0.0" sentencenodepath="1">La publicación recuerda también las fechas de <argset><head>pago </head><argument argument="arg1" function="cn" thematicrole="pat" type="sp">de impuestos</argument></argset>. </example>
        <example file="CESS-CAST-P/154_20010102.tbf.xml" nodepath="1.3.3.3.5.1.0.0" sentencenodepath="1">Jörg_Frick , el abogado de la ex campeona , sin entrar a comentar las cifras , ha confirmado que su cliente ha retirado la demanda contra el fisco y Ø ha aceptado pagar sus deudas , porque Ø no ha tenido que hacer_frente al <argset><head>pago </head><argument argument="arg1" function="cn" thematicrole="pat" type="sp">de impuestos</argument></argset>en Estados_Unidos , donde Ø tiene fijada actualmente su residencia . </example>
        <example file="CESS-CAST-P/58_20010602.tbf.xml" nodepath="0.3.1.1.1.1.1.0" sentencenodepath="0">El Gobierno argentino depositó ayer el dinero comprometido para <argset><specifier>el</specifier><head>pago </head><argument argument="arg1" function="cn" thematicrole="pat" type="sp">de salario</argument><argument argument="arg2" function="cn" thematicrole="ben" type="sp">a los empleados de Aerolíneas_Argentinas</argument></argset>, lo que puede abrir una nueva vía de negociación para solucionar el conflicto de esta compañía . </example>
        <example file="CESS-CAST-P/63_20010901.tbf.xml" nodepath="11.0.1.1.0" sentencenodepath="11">Tras <argset><specifier>el</specifier><head>pago </head><argument argument="arg1" function="cn" thematicrole="pat" type="sp">de tres millones de pesetas</argument></argset>, los niños eran inscritos en el registro como hijos biológicos del padre adoptante , que se hacía con la custodia . </example>
        <example file="CESS-CAST-P/98_19990302.tbf.xml" nodepath="5.3.1.1.0" sentencenodepath="5">El crédito de 8.500 millones de pesetas del ICO se liquidó con <argset><specifier>el</specifier><head>pago </head><argument argument="arg1" function="cn" thematicrole="pat" type="sp">de sólo 1.100 millones</argument></argset>. </example>
      </examples>
    </frame>
  </sense>
  <sense alternativelemma="balanza_de_pagos" cousin="no" denotation="result" id="3" lexicalizationtype="nominal" lexicalized="yes" originlemma="pagar" originlink="verb.pagar.1" wordnetsynset="16:00725730">
    <frame appearsinplural="yes" type="default">
      <specifiers>
        <constituent frequency="1" type="void"/>
      </specifiers>
      <examples>
        <example file="CESS-CAST-P/94_19990601.tbf.xml" nodepath="0.0.1.1.1.1.1.1.0.0" sentencenodepath="0">El déficit de la balanza de <argset><head>pagos </head></argset>fue de casi 80.000 millones hasta marzo . </example>
      </examples>
    </frame>
  </sense>
</lexentry>
