<?xml version="1.0" encoding="UTF-8" standalone="no"?>
<!-- 

  ancoralex-2.0.3
       
			Copyright (C) 2007,2008,2009,2010,2011 CLiC - UB
			Centre de Llenguatge i Computació - Universitat de Barcelona
 
  This file is part of ancoralex-2.0.3.
 
  ancoralex-2.0.3 is free software and data: you can redistribute it and/or modify
  it under the terms of the GNU General Public License as published
  by the Free Software Foundation, either version 3 of the License,
  or (at your option) any later version.

  ancoralex-2.0.3 is distributed in the hope that it will be useful,
  but WITHOUT ANY WARRANTY; without even the implied warranty of
  MERCHANTABILITY or FITNESS FOR A PARTICULAR PURPOSE.  See the
  GNU General Public License for more details.
 
  You should have received a copy of the GNU General Public License
  along with ancoralex-2.0.3.  If not, see &lt;http://www.gnu.org/licenses/&gt;.
 
  Check a text in catalan explaining the terms of the license at http://www.softcatala.cat/wiki/GPL3.
  In spanish at http://www.viti.es/gnu/licenses/gpl.html
  
  The following paper must be cited when using verb lexicon: 

 * Aparicio, Juan, Mariona Taulé, M.Antònia Martí (2008) 'AnCora-Verb: A Lexical Resource for 
   the Semantic Annotation of Corpora'. Proceedings of 6th International Conference on Language 
   Resources and Evaluation. Marrakesh (Morocco).

  The following paper must be cited when using noun lexicon: 

 * Peris, Aina, Mariona Taulé (2011). AnCora-Nom: A Spanish lexicon of deverbal nominalizations. 
   Procesamiento del Lenguaje Natural, nº46, pp. 11-18.
 
 

 

-->

<lexentry lemma="coordinación" lng="es" origin="deverbal" type="noun">
  <sense cousin="no" denotation="result" id="1" lexicalized="no" originlemma="coordinar" originlink="verb.coordinar.1" wordnetsynset="16:04363056">
    <frame appearsinplural="no" type="default">
      <specifiers>
        <constituent frequency="1" postype="article" type="determiner"/>
      </specifiers>
      <examples>
        <example file="CESS-CAST-P/132_20001202.tbf.xml" nodepath="2.2.2.1.0" sentencenodepath="2">Ø Asegura que en adelante <argset><specifier>la</specifier><head>coordinación </head></argset>no volverá a fallar . </example>
      </examples>
    </frame>
  </sense>
  <sense cousin="no" denotation="event" id="2" lexicalized="no" originlemma="coordinar" originlink="verb.coordinar.1" wordnetsynset="16:00515970">
    <frame appearsinplural="no" type="default">
      <argument argument="arg1" thematicrole="pat">
        <constituent frequency="1" preposition="entre" type="sp"/>
        <constituent frequency="1" preposition="de" type="sp"/>
      </argument>
      <argument argument="argM" thematicrole="fin">
        <constituent frequency="1" preposition="para" type="sp"/>
      </argument>
      <specifiers>
        <constituent frequency="2" postype="article" type="determiner"/>
        <constituent frequency="1" type="void"/>
      </specifiers>
      <reference_modifiers>
        <constituent frequency="1" type="S"/>
        <constituent frequency="1" type="s.a"/>
      </reference_modifiers>
      <examples>
        <example file="CESS-CAST-A/14332_20000618.tbf.xml" nodepath="9.2.1.0" sentencenodepath="9">El enfoque tradicional de las operaciones conjuntas ha sido <argset><specifier>la</specifier><head>coordinación </head><argument argument="arg1" function="cn" thematicrole="pat" type="sp">entre las diferentes armas</argument><argument argument="argM" function="cn" thematicrole="fin" type="sp">para evitar que una duplique o interfiera con las demás</argument></argset>. </example>
        <example file="CESS-CAST-AA/19561_20000830.tbf.xml" nodepath="3.4.1.2.1.2.1.1.1.0.6.0" sentencenodepath="3">En el documento final , de nueve puntos , se reconoció " la urgente necesidad de que los países miembros utilicen plenamente y Ø fortalezcan los sistemas de <argset>prevención , vigilancia epidemiológica , información , <head>coordinación </head>y cooperación </argset>" disponibles en los numerosos acuerdos regionales . </example>
        <example file="CESS-CAST-P/68_19990902.tbf.xml" nodepath="4.2.2.3.1.2.1" sentencenodepath="4">La polémica orden sobre los criterios para cubrir las vacantes de magistrados indicaba que " en ningún caso " se designarían magistrados para completar ninguna plaza en casos de permisos , asistencia a cursos , funciones asociativas o supuestos similares , y Ø señalaba que estas circunstancias deberían solventarse mediante <argset>" <specifier>la</specifier>
            <reference_modifiers>adecuada</reference_modifiers>
            <head>coordinación </head>
            <reference_modifiers>interna</reference_modifiers>
            <argument argument="arg1" function="cn" thematicrole="pat" type="sp">del tribunal</argument>" </argset>. </example>
      </examples>
    </frame>
  </sense>
  <sense cousin="no" denotation="result" id="3" lexicalized="no" originlemma="coordinar" originlink="verb.coordinar.2" wordnetsynset="16:04734393">
    <frame appearsinplural="no" type="default">
      <specifiers>
        <constituent frequency="6" type="void"/>
      </specifiers>
      <examples>
        <example file="CESS-CAST-A/10656_20001214.tbf.xml" nodepath="2.2.1.1.1.1.0.2.1.0.0" sentencenodepath="2">Estas declaraciones tuvieron_lugar tras una reunión del comité bilateral de <argset><head>coordinación </head></argset>de Arabia_Saudí y Yemen celebrada en Yeda , en la costa saudí del Mar_Rojo . </example>
        <example file="CESS-CAST-A/10656_20001214.tbf.xml" nodepath="4.2.1.1.1.0.1.1.0.0" sentencenodepath="4">Abdel_Aziz consideró la reunión del comité de <argset><head>coordinación </head></argset>un primer paso en el desarrollo de la cooperación entre los dos países , aunque Ø advirtió de que no deben esperarse resultados inmediatos . </example>
        <example file="CESS-CAST-A/10656_20001214.tbf.xml" nodepath="6.0.1.1.1.0.0" sentencenodepath="6">El comité de <argset><head>coordinación </head></argset>acordó reunirse cada seis meses e intercambiar visitas periódicas para estudiar nuevas oportunidades de inversión . </example>
        <example file="CESS-CAST-AA/9294_20000512.tbf.xml" nodepath="3.1.4.2.1.1.1.0.0" sentencenodepath="3">para Méndez la reducción de la jornada laboral a 35 horas semanales , el cumplimiento de la Ley_de_Prevención_de_Riesgos_Laborales por_parte_de los empresarios y " mejorar los mecanismos de <argset><head>coordinación </head></argset>entre las administraciones autonómicas y el Gobierno " son fines prioritarios para tratar en esta negociación . </example>
        <example file="CESS-CAST-P/113_20000201.tbf.xml" nodepath="3.2.1.1.1.0.0" sentencenodepath="3">Los sindicatos anunciaron una estrategia de <argset><head>coordinación </head></argset>internacional para controlar el destino de las inversiones de los fondos de pensiones de trabajadores . </example>
        <example file="CESS-CAST-P/18_19990701.tbf.xml" nodepath="4.3.1.1.0.2.1.1.0.0" sentencenodepath="4">El origen de la actual situación no es otra_que la improvisación y falta de <argset><head>coordinación </head></argset>a la hora de planificar con suficiente adelanto las necesidades de nuestra sociedad , tanto de médicos en general ( Ø somos el país europeo con mayor proporción de estos profesionales por número de habitantes ) como del exceso de especialidades médicas existentes ( Ø somos después de Italia el que tiene mayor número ) y también del número de especialistas en algunas de ellas , si_bien es cierto que en algunos periodos han existido déficits . </example>
      </examples>
    </frame>
  </sense>
  <sense cousin="no" denotation="event" id="4" lexicalized="no" originlemma="coordinar" originlink="verb.coordinar.2" wordnetsynset="16:00515970">
    <frame appearsinplural="no" type="default">
      <argument argument="arg1" thematicrole="pat">
        <constituent frequency="1" preposition="de" type="sp"/>
      </argument>
      <specifiers>
        <constituent frequency="1" postype="article" type="determiner"/>
      </specifiers>
      <reference_modifiers>
        <constituent frequency="1" type="s.a"/>
      </reference_modifiers>
      <examples>
        <example file="CESS-CAST-A/15624_20001019.tbf.xml" nodepath="12.0.1.1.1.1.0" sentencenodepath="12">El candidato a <argset><specifier>la</specifier><head>coordinación </head><reference_modifiers>general</reference_modifiers><argument argument="arg1" function="cn" thematicrole="pat" type="sp">de IU</argument></argset>Gaspar_Llamazares dijo que con esta fusión el Gobierno " facilita de_nuevo la conversión del monopolio público del sector eléctrico en un monopolio privado con claras conexiones políticas " . </example>
      </examples>
    </frame>
  </sense>
</lexentry>
